setup.py
config/__init__.py
config/conf.py
fileconfiguration.egg-info/PKG-INFO
fileconfiguration.egg-info/SOURCES.txt
fileconfiguration.egg-info/dependency_links.txt
fileconfiguration.egg-info/top_level.txt