Metadata-Version: 2.1
Name: fileconfiguration
Version: 0.1
Summary: A Fileconfiguration for JSON
Home-page: 
Author: prodbyprocess
Author-email: manuel.staufervb@gmail.com
